ocx_common/__init__.py
ocx_common/clients/__init__.py
ocx_common/clients/clients.py
ocx_common/clients/wiki_client.py
ocx_common/clients/wiki_struct_data.py
ocx_common/decorators/__init__.py
ocx_common/decorators/decorators.py
ocx_common/interfaces/__init__.py
ocx_common/interfaces/interfaces.py
ocx_common/loader/__init__.py
ocx_common/loader/loader.py
ocx_common/parser/__init__.py
ocx_common/parser/parsers.py
ocx_common/parser/xml_document_parser.py
ocx_common/serializer/__init__.py
ocx_common/serializer/serializer.py
ocx_common/serializer/resource/gitb_trl_stylesheet_v1.0.xsl
ocx_common/utilities/__init__.py
ocx_common/utilities/downloader.py
ocx_common/utilities/ocx_xml.py
ocx_common/utilities/utilities.py
ocx_common/utilities/validation.py
ocx_common/x_path/__init__.py
ocx_common/x_path/x_path.py
ocx_common/x_path/xelement.py
ocx_common-2.6.1.dist-info/METADATA
ocx_common-2.6.1.dist-info/WHEEL
ocx_common-2.6.1.dist-info/licenses/LICENSE
ocx_common-2.6.1.dist-info/RECORD
